LbSoftConfDB/SoftConfDB.py
LbSoftConfDB/__init__.py
LbSoftConfDB/py2neo/__init__.py
LbSoftConfDB/py2neo/admin.py
LbSoftConfDB/py2neo/calendar.py
LbSoftConfDB/py2neo/cypher.py
LbSoftConfDB/py2neo/geoff.py
LbSoftConfDB/py2neo/gremlin.py
LbSoftConfDB/py2neo/neo4j.py
LbSoftConfDB/py2neo/neometry.py
LbSoftConfDB/py2neo/rest.py
LbSoftConfDB/py2neo/subgraph.py
LbSoftConfDB/py2neo/util.py
LbSoftConfDBMigration/LbSoftConfDBMigration.py
LbSoftConfDBMigration/__init__.py
LbSoftConfDBMigration-0.0.1.dist-info/METADATA
LbSoftConfDBMigration-0.0.1.dist-info/WHEEL
LbSoftConfDBMigration-0.0.1.dist-info/entry_points.txt
LbSoftConfDBMigration-0.0.1.dist-info/top_level.txt
LbSoftConfDBMigration-0.0.1.dist-info/zip-safe
LbSoftConfDBMigration-0.0.1.dist-info/RECORD
